genesis_devtools/__init__.py
genesis_devtools/constants.py
genesis_devtools/exceptions.py
genesis_devtools/logger.py
genesis_devtools/utils.py
genesis_devtools/backup/backup.py
genesis_devtools/backup/base.py
genesis_devtools/backup/local.py
genesis_devtools/backup/qcow.py
genesis_devtools/backup/s3.py
genesis_devtools/builder/__init__.py
genesis_devtools/builder/base.py
genesis_devtools/builder/builder.py
genesis_devtools/builder/dependency.py
genesis_devtools/builder/packer.py
genesis_devtools/cmd/__init__.py
genesis_devtools/cmd/cli.py
genesis_devtools/infra/driver/base.py
genesis_devtools/infra/driver/libvirt.py
genesis_devtools/infra/libvirt/__init__.py
genesis_devtools/infra/libvirt/constants.py
genesis_devtools/infra/libvirt/libvirt.py
genesis_devtools/packer/debian_12/debian-12.pkr.hcl
genesis_devtools/packer/debian_12/plugins.pkr.hcl
genesis_devtools/packer/genesis_base/genesis-base.pkr.hcl
genesis_devtools/packer/genesis_base/plugins.pkr.hcl
genesis_devtools/packer/genesis_core/genesis-core.pkr.hcl
genesis_devtools/packer/genesis_core/plugins.pkr.hcl
genesis_devtools/packer/genesis_custom/genesis-custom.pkr.hcl
genesis_devtools/packer/genesis_custom/plugins.pkr.hcl
genesis_devtools/packer/ubuntu_24/plugins.pkr.hcl
genesis_devtools/packer/ubuntu_24/ubuntu-24.pkr.hcl
genesis_devtools/repo/__init__.py
genesis_devtools/repo/base.py
genesis_devtools/repo/fs.py
genesis_devtools/repo/nginx.py
genesis_devtools/repo/utils.py
genesis_devtools/stand/__init__.py
genesis_devtools/stand/models.py
genesis_devtools/tests/__init__.py
genesis_devtools/tests/unit/__init__.py
genesis_devtools/tests/unit/conftest.py
genesis_devtools/tests/unit/test_basic.py
genesis_devtools/tests/unit/test_builder.py
genesis_devtools/tests/unit/test_cmd_backup.py
genesis_devtools/tests/unit/test_dependency.py
genesis_devtools/tests/unit/test_domains_for_backup.py
genesis_devtools/tests/unit/test_packer.py
genesis_devtools-0.8.0.dist-info/licenses/AUTHORS
genesis_devtools-0.8.0.dist-info/licenses/LICENSE
genesis_devtools-0.8.0.dist-info/METADATA
genesis_devtools-0.8.0.dist-info/WHEEL
genesis_devtools-0.8.0.dist-info/entry_points.txt
genesis_devtools-0.8.0.dist-info/pbr.json
genesis_devtools-0.8.0.dist-info/top_level.txt
genesis_devtools-0.8.0.dist-info/RECORD
